dataclass_dict/__init__.py
dataclass_dict/__version__.py
dataclass_dict/threaded_request.py
dataclass_dict/utils.py
dataclass_dict-0.0.6.dist-info/LICENSE
dataclass_dict-0.0.6.dist-info/METADATA
dataclass_dict-0.0.6.dist-info/WHEEL
dataclass_dict-0.0.6.dist-info/top_level.txt
dataclass_dict-0.0.6.dist-info/RECORD
