Metadata-Version: 2.1
Name: dataclass-dict
Version: 0.0.6
Summary: With this package you are able to create a dataclass that works exactly like a dictionary.
Home-page: https://github.com/Cerberus1746/dataclass_dict
Author: Leandro (Cerberus1746) Benedet Garcia
Author-email: leandro.benedet.garcia@gmail.com
License: MIT License
Platform: UNKNOWN
Classifier: Programming Language :: Python :: 3 :: Only
Classifier: Programming Language :: Python :: 3.6
Classifier: Programming Language :: Python :: 3.7
Classifier: Programming Language :: Python :: 3.8
Classifier: Programming Language :: Python :: Implementation :: CPython
Classifier: Programming Language :: Python :: Implementation :: PyPy
Classifier: License :: OSI Approved :: MIT License
Classifier: Operating System :: OS Independent
Classifier: Development Status :: 4 - Beta
Classifier: Intended Audience :: Developers
Classifier: Topic :: Software Development
Classifier: Topic :: Software Development :: Libraries
Classifier: Topic :: Utilities
Classifier: Topic :: Internet
Requires-Python: >=3.6
Requires-Dist: typing-extensions
Provides-Extra: docs
Requires-Dist: sphinx-rtd-theme ; extra == 'docs'
Requires-Dist: sphinx-autodoc-typehints ; extra == 'docs'
Requires-Dist: Sphinx ; extra == 'docs'
Provides-Extra: tests
Requires-Dist: pytest-localserver ; extra == 'tests'
Requires-Dist: pytest-pylint ; extra == 'tests'
Requires-Dist: pytest-runner ; extra == 'tests'
Requires-Dist: python-coveralls ; extra == 'tests'
Requires-Dist: mypy ; extra == 'tests'
